{
  "lang": "en",
  "dir": "ltr",
  "pageName": "channel",
  "title": "ALJ Channel Page",

  "featuredCarousel": {
    "items": [
      {
        "title": "slide 1",
        "description": "Contrary to popular belief, Lorem Ipsum is not simply random text. It has roots in a piece of classical Latin literature from 45 BC, making it over 2000 years old.",
        "thumbnail": "http://placeimg.com/1280/412/any?1",
        "show": "Americas",
        "duration": "06:24",
        "date": "Feb 3, 2013"
      },
      {
        "title": "slide 2",
        "description": "Contrary to popular belief, Lorem Ipsum is not simply random text. It has roots in a piece of classical Latin literature from 45 BC, making it over 2000 years old.",
        "thumbnail": "http://placeimg.com/1280/412/any?1",
        "show": "Americas",
        "duration": "06:24",
        "date": "Feb 3, 2013"
      },
      {
        "title": "slide 3",
        "description": "Contrary to popular belief, Lorem Ipsum is not simply random text. It has roots in a piece of classical Latin literature from 45 BC, making it over 2000 years old.",
        "thumbnail": "http://placeimg.com/1280/412/any?1",
        "show": "Americas",
        "duration": "06:24",
        "date": "Feb 3, 2013"
      },
      {
        "title": "slide 4",
        "description": "Contrary to popular belief, Lorem Ipsum is not simply random text. It has roots in a piece of classical Latin literature from 45 BC, making it over 2000 years old.",
        "thumbnail": "http://placeimg.com/1280/412/any?1",
        "show": "Americas",
        "duration": "06:24",
        "date": "Feb 3, 2013"
      }
    ]
  },

  "carousels": [
    {
      "title": "Shows",
      "channelID": 1111,
      "items": [
        { "date": "08-29-2012", "views": 10, "title": "Gore Vidal", "description": "Lorem ipsum dolor sit amet, consectetur adipisicing elit, sed do eiusmod tempor incididunt ut labore et dolore magna aliqua." },
        { "date": "08-28-2012", "views": 15, "title": "Phoning from the Philippines", "description": "Test description lorem ipsum dolar the quick brown fox jumped over the lazy dog! The quick brown fox, it jumped over the lazy dog." },
        { "date": "08-27-2012", "views": 32, "title": "Wole Soyinka", "description": "Test description lorem ipsum dolar the quick brown fox jumped over the lazy dog! The quick brown fox, it jumped over the lazy dog." },
        { "date": "08-27-2012", "views": 61, "title": "Wole Soyinka", "description": "Test description lorem ipsum dolar the quick brown fox jumped over the lazy dog! The quick brown fox, it jumped over the lazy dog." },
        { "date": "08-27-2012", "views": 44, "title": "Wole Soyinka", "description": "Test description lorem ipsum dolar the quick brown fox jumped over the lazy dog! The quick brown fox, it jumped over the lazy dog." },
        { "date": "08-27-2012", "views": 23, "title": "Wole Soyinka", "description": "Test description lorem ipsum dolar the quick brown fox jumped over the lazy dog! The quick brown fox, it jumped over the lazy dog." }
      ]
    },

    {
      "title": "News Clips",
      "channelID": 2222,
      "items": [
        { "date": "08-29-2012", "views": 10, "title": "Blast near presidential palace in Damascus" },
        { "date": "08-28-2012", "views": 15, "title": "Obama says Americans must demand stricter gun control" },
        { "date": "08-28-2012", "views": 15, "title": "Obama says Americans must demand stricter gun control" },
        { "date": "08-28-2012", "views": 15, "title": "Obama says Americans must demand stricter gun control" },
        { "date": "08-28-2012", "views": 15, "title": "Obama says Americans must demand stricter gun control" },
        { "date": "08-28-2012", "views": 15, "title": "Obama says Americans must demand stricter gun control" }
      ]
    }
  ]

}
